{
  "name": "duckdb-usd-extension",
  "version": "0.1.0",
  "dependencies": [
    "vcpkg-cmake",
    {
      "name": "usd",
      "version>=": "25.8"
    },
    "boost-filesystem",
    "tbb"
  ],
  "vcpkg-configuration": {
    "registries": [
      {
        "kind": "git",
        "repository": "https://github.com/duckdb/vcpkg-duckdb-ports",
        "baseline": "c8f9d504986e76dbcd4585a34028ff00e251f40f",
        "packages": [ "vcpkg-cmake" ]
      }
    ]
  },
  "builtin-baseline" : "e9b9012b4eea442947623fa7811aaa6c8ab7fde4"
}

